gempaterkirni/__init__.py
Latest_IDEarthquake-0.0.8.dist-info/LICENSE
Latest_IDEarthquake-0.0.8.dist-info/METADATA
Latest_IDEarthquake-0.0.8.dist-info/WHEEL
Latest_IDEarthquake-0.0.8.dist-info/top_level.txt
Latest_IDEarthquake-0.0.8.dist-info/RECORD
