Metadata-Version: 2.1
Name: Latest-IDEarthquake
Version: 0.0.8
Summary: This package will scrape Indonesia's latest earthquake data from bmkg.go.id
Home-page: https://github.com/RemoteWorkerIDN/Latest_IDEarthquake
Author: danahiswara
Author-email: danahiswara.danas@gmail.com
License: Development Status :: 4 - Beta
License-File: LICENSE
